element_facemap/__init__.py
element_facemap/facial_behavior_estimation.py
element_facemap/version.py
element_facemap-0.1.7.dist-info/LICENSE
element_facemap-0.1.7.dist-info/METADATA
element_facemap-0.1.7.dist-info/WHEEL
element_facemap-0.1.7.dist-info/top_level.txt
element_facemap-0.1.7.dist-info/RECORD
