Metadata-Version: 2.1
Name: element-facemap
Version: 0.1.7
Summary: Facemap DataJoint element
Home-page: https://github.com/datajoint/element-facemap
Author: DataJoint
Author-email: info@datajoint.com
License: MIT
Keywords: neuroscience facemap science datajoint
Platform: UNKNOWN
License-File: LICENSE
Requires-Dist: datajoint >=0.13.0
Requires-Dist: element-interface >=0.3.0
Requires-Dist: opencv-python-headless
